_bo4e_generator_version.py
bo4e_generator/__init__.py
bo4e_generator/__main__.py
bo4e_generator/imports.py
bo4e_generator/parser.py
bo4e_generator/py.typed
bo4e_generator/schema.py
bo4e_generator/sqlparser.py
bo4e_generator/custom_templates/BaseModel.jinja2
bo4e_generator/custom_templates/Config.jinja2
bo4e_generator/custom_templates/Enum.jinja2
bo4e_generator/custom_templates/ManyLinks.jinja2
bo4e_python_generator-0.0.13.dist-info/METADATA
bo4e_python_generator-0.0.13.dist-info/WHEEL
bo4e_python_generator-0.0.13.dist-info/entry_points.txt
bo4e_python_generator-0.0.13.dist-info/RECORD
