Metadata-Version: 2.3
Name: BO4E-Python-Generator
Version: 0.0.13
Summary: This tool auto generates (customizable) pydantic v2 Code to implement the BO4E-Schemas.
Project-URL: Changelog, https://github.com/bo4e/bo4e-python-generator/releases
Project-URL: Homepage, https://github.com/bo4e/bo4e-python-generator
Author-email: Hochfrequenz Unternehmensberatung GmbH <info@hochfrequenz.de>
License: MIT
Keywords: bo4e,code-generator
Classifier: Development Status :: 4 - Beta
Classifier: Environment :: Console
Classifier: Intended Audience :: Developers
Classifier: License :: OSI Approved :: MIT License
Classifier: Operating System :: OS Independent
Classifier: Programming Language :: Python
Classifier: Programming Language :: Python :: 3 :: Only
Classifier: Programming Language :: Python :: 3.11
Classifier: Programming Language :: Python :: 3.12
Requires-Python: >=3.11
Requires-Dist: click
Requires-Dist: datamodel-code-generator
